elastica_rhino/__init__.py
elastica_rhino/callback.py
elastica_rhino/collector.py
elastica_rhino/version.py
elastica_rhino-0.1.1.dist-info/LICENSE
elastica_rhino-0.1.1.dist-info/METADATA
elastica_rhino-0.1.1.dist-info/WHEEL
elastica_rhino-0.1.1.dist-info/top_level.txt
elastica_rhino-0.1.1.dist-info/RECORD
