Metadata-Version: 2.1
Name: elastica-rhino
Version: 0.1.1
Summary: Rhino plugin and PyElastica extension for data visualization.
Home-page: https://github.com/skim0119/PyElastica-to-Rhino
Author: skim0119
Author-email: skim449@illinois.edu
License: MIT
Download-URL: https://github.com/skim0119/PyElastica-to-Rhino/archive/refs/tags/v0.1.1.tar.gz
Platform: UNKNOWN
Classifier: License :: OSI Approved :: MIT License
Classifier: Development Status :: 2 - Pre-Alpha
Classifier: Framework :: Robot Framework :: Library
Classifier: Programming Language :: Python :: 3.8
Classifier: Intended Audience :: Science/Research
Classifier: Intended Audience :: Education
Requires-Python: >=3.8.0
Requires-Dist: pyelastica (>=0.2.0)
Requires-Dist: numpy (>=1.20.0)
